{"ForbiddenJawbreaker:WidhillOnTheWater:colony":{"activeResearchCount":0,"getDissatisfiedCitizens":0,"getRequests":0,"unguardedBuildingCount":0,"getSickCitizens":0,"getHungryCitizens":0,"getCitizens":108,"getWorkingCitizens":0,"getAverageBuildingLevel":4.96,"getIdleCitizens":108,"getWorkOrders":0,"unstaffedBuldingCount":2,"name":"ForbiddenJawbreaker:WidhillOnTheWater:colony","getSleepingCitizens":0,"guardedBuildingCount":99,"finishedResearchCount":0,"getCitizenHappiness":10},"timeStamp":1741321857657}